[
  {
    "name": "themes",
    "items": [
      {
        "title": "Very long name of some theme as example",
        "items": [
          "Another one sublink",
          "Another one sublink",
          "Another one sublink",
          "Another one sublink"
        ]
      },
      {
        "title": "Very long name of some theme as example",
        "items": [
          "Another one sublink",
          "Another one sublink",
          "Another one sublink",
          "Another one sublink"
        ]
      },
      {
        "title": "Very long name of some theme as example",
        "items": [
          "Another one sublink",
          "Another one sublink",
          "Another one sublink",
          "Another one sublink"
        ]
      },
      {
        "title": "Very long name of some theme as example",
        "items": [
          "Another one sublink",
          "Another one sublink",
          "Another one sublink",
          "Another one sublink"
        ]
      },
      {
        "title": "Very long name of some theme as example",
        "items": [
          "Another one sublink",
          "Another one sublink",
          "Another one sublink",
          "Another one sublink"
        ]
      },
      {
        "title": "Very long name of some theme as example",
        "items": [
          "Another one sublink",
          "Another one sublink",
          "Another one sublink",
          "Another one sublink"
        ]
      },
      {
        "title": "Very long name of some theme as example",
        "items": [
          "Another one sublink",
          "Another one sublink",
          "Another one sublink",
          "Another one sublink"
        ]
      },
      {
        "title": "Very long name of some theme as example",
        "items": [
          "Another one sublink",
          "Another one sublink",
          "Another one sublink",
          "Another one sublink"
        ]
      }
    ]
  }
]
